gangplank/__init__.py
gangplank/prometheus_model.py
gangplank/train_test_exporter.py
gangplank-0.5.0.dist-info/METADATA
gangplank-0.5.0.dist-info/WHEEL
gangplank-0.5.0.dist-info/licenses/LICENSE
gangplank-0.5.0.dist-info/RECORD
